toronado/__init__.py
toronado/__main__.py
toronado-0.1.0.dist-info/LICENSE
toronado-0.1.0.dist-info/METADATA
toronado-0.1.0.dist-info/WHEEL
toronado-0.1.0.dist-info/top_level.txt
toronado-0.1.0.dist-info/RECORD
